radio_duck/__init__.py
radio_duck/connection_test.py
radio_duck/cursor_test.py
radio_duck/db.py
radio_duck/db_types.py
radio_duck/db_types_test.py
radio_duck/dialect_test.py
radio_duck/exceptions.py
radio_duck/globals.py
radio_duck/queries.py
radio_duck/reserved_keywords.py
radio_duck/sqlalchemy.py
district5-0.1.18.dist-info/LICENSE
district5-0.1.18.dist-info/METADATA
district5-0.1.18.dist-info/WHEEL
district5-0.1.18.dist-info/RECORD
